[
    {
        "name" : "Omar Faruk ",
        "email":"faruk@gmail.com",
        "image" : "",
        "service_ID" : "636b1fe0ba91a2efff9d7eb7",
        "massage" : "This is a good product",
        "review": "5"
    },
    {
        "name" : "Omar Faruk ",
        "email":"faruk@gmail.com",
        "image" : "",
        "service_ID" : "636b1fe0ba91a2efff9d7eb3",
        "massage" : "This is a good product",
        "review": "5"
    },
    {
        "name" : "Omar Faruk ",
        "email":"faruk@gmail.com",
        "image" : "",
        "service_ID" : "636b1fe0ba91a2efff9d7eb5",
        "massage" : "This is a good product",
        "review": "5"
    },
    {
        "name" : "Omar Faruk ",
        "email":"omar@gmail.com",
        "image" : "",
        "service_ID" : "636b1fe0ba91a2efff9d7eb7",
        "massage" : "This is a good product",
        "review": "5"
    },
    {
        "name" : "Omar Faruk ",
        "email":"omar@gmail.com",
        "image" : "",
        "service_ID" : "636b1fe0ba91a2efff9d7eb5",
        "massage" : "This is a good product",
        "review": "5"
    },
    {
        "name" : "Omar Faruk ",
        "email":"omar@gmail.com",
        "image" : "",
        "service_ID" : "636b1fe0ba91a2efff9d7eb7",
        "massage" : "This is a good product",
        "review": "5"
    }
]